monadic_context/__init__.py
monadic_context/context.py
monadic_context/defer.py
monadic_context/pipe.py
monadic_context-0.2.2.dist-info/LICENSE
monadic_context-0.2.2.dist-info/METADATA
monadic_context-0.2.2.dist-info/WHEEL
monadic_context-0.2.2.dist-info/RECORD
