Metadata-Version: 2.3
Name: monadic-context
Version: 0.2.2
Summary: A lightweight, type-safe dependency injection library
License: MIT
Author: Sean Haugh
Author-email: sean@lfo.team
Requires-Python: >=3.9
Classifier: Programming Language :: Python :: 3.9
Classifier: Programming Language :: Python :: 3.10
Classifier: Programming Language :: Python :: 3.11
Classifier: Programming Language :: Python :: 3.12
Classifier: Programming Language :: Python :: 3.13
Classifier: License :: OSI Approved :: MIT License
Classifier: Topic :: Software Development :: Libraries :: Python Modules
Classifier: Typing :: Typed
Requires-Dist: typing_extensions (>=4.13.2,<5.0.0) ; python_version < "3.11"
